maflib/MAF.py
maflib/MAFIndex.py
maflib/__init__.py
maflib-1.0.0.dist-info/COPYING
maflib-1.0.0.dist-info/COPYING.LESSER
maflib-1.0.0.dist-info/METADATA
maflib-1.0.0.dist-info/WHEEL
maflib-1.0.0.dist-info/top_level.txt
maflib-1.0.0.dist-info/RECORD
