Metadata-Version: 2.1
Name: maflib
Version: 1.0.0
Summary: Library for reading and manipulating Mozilla Archive Format (MAF) files
Home-page: https://github.com/projreality/maflib
Author: Samuel Li
Author-email: sam@projreality.com
License: https://www.gnu.org/licenses/lgpl.html
Platform: UNKNOWN
Requires-Dist: python-dateutil
